deepface/DeepFace.py
deepface/__init__.py
deepface/api/__init__.py
deepface/api/postman/deepface-api.postman_collection.json
deepface/api/src/__init__.py
deepface/api/src/api.py
deepface/api/src/app.py
deepface/api/src/modules/__init__.py
deepface/api/src/modules/core/__init__.py
deepface/api/src/modules/core/routes.py
deepface/api/src/modules/core/service.py
deepface/commons/__init__.py
deepface/commons/constant.py
deepface/commons/file_utils.py
deepface/commons/folder_utils.py
deepface/commons/image_utils.py
deepface/commons/logger.py
deepface/commons/package_utils.py
deepface/models/Demography.py
deepface/models/Detector.py
deepface/models/FacialRecognition.py
deepface/models/__init__.py
deepface/models/demography/Age.py
deepface/models/demography/Emotion.py
deepface/models/demography/Gender.py
deepface/models/demography/Race.py
deepface/models/demography/__init__.py
deepface/models/face_detection/CenterFace.py
deepface/models/face_detection/Dlib.py
deepface/models/face_detection/FastMtCnn.py
deepface/models/face_detection/MediaPipe.py
deepface/models/face_detection/MtCnn.py
deepface/models/face_detection/OpenCv.py
deepface/models/face_detection/RetinaFace.py
deepface/models/face_detection/Ssd.py
deepface/models/face_detection/Yolo.py
deepface/models/face_detection/YuNet.py
deepface/models/face_detection/__init__.py
deepface/models/facial_recognition/ArcFace.py
deepface/models/facial_recognition/DeepID.py
deepface/models/facial_recognition/Dlib.py
deepface/models/facial_recognition/Facenet.py
deepface/models/facial_recognition/FacenetONNX.py
deepface/models/facial_recognition/FbDeepFace.py
deepface/models/facial_recognition/GhostFaceNet.py
deepface/models/facial_recognition/OpenFace.py
deepface/models/facial_recognition/SFace.py
deepface/models/facial_recognition/VGGFace.py
deepface/models/facial_recognition/__init__.py
deepface/models/spoofing/FasNet.py
deepface/models/spoofing/FasNetBackbone.py
deepface/models/spoofing/__init__.py
deepface_facescore-0.4.8.dist-info/LICENSE
deepface_facescore-0.4.8.dist-info/METADATA
deepface_facescore-0.4.8.dist-info/WHEEL
deepface_facescore-0.4.8.dist-info/RECORD
